MANIFEST.in
README.txt
setup.py
docs/HISTORY.txt
docs/cycle de vie.png
docs/installation-os-debian-5.0-lenny.rst
docs/installation-os-debian-6.0-squeeze.rst
docs/installation-os-ubuntu-10.04.rst
docs/presentation.zargo
docs/unis-zopeskel-usage.txt
docs/testfiles/unis-default.save
zopeskel/__init__.py
zopeskel.unis.egg-info/PKG-INFO
zopeskel.unis.egg-info/SOURCES.txt
zopeskel.unis.egg-info/dependency_links.txt
zopeskel.unis.egg-info/entry_points.txt
zopeskel.unis.egg-info/namespace_packages.txt
zopeskel.unis.egg-info/not-zip-safe
zopeskel.unis.egg-info/requires.txt
zopeskel.unis.egg-info/top_level.txt
zopeskel/unis/__init__.py
zopeskel/unis/abstract_buildout.py
zopeskel/unis/templates.py
zopeskel/unis/templates/unis_plone4_buildout/README.txt
zopeskel/unis/templates/unis_plone4_buildout/bootstrap.py
zopeskel/unis/templates/unis_plone4_buildout/buildout.cfg_tmpl
zopeskel/unis/templates/unis_plone4_buildout/downloads/README.txt
zopeskel/unis/templates/unis_plone4_buildout/patchs/LDAPUserFolder.patch
zopeskel/unis/templates/unis_plone4_buildout/profiles/development.cfg_tmpl
zopeskel/unis/templates/unis_plone4_buildout/profiles/preproduction.cfg_tmpl
zopeskel/unis/templates/unis_plone4_buildout/profiles/production.cfg_tmpl
zopeskel/unis/templates/unis_plone4_buildout/profiles/standalone.cfg_tmpl
zopeskel/unis/templates/unis_plone4_buildout/profiles/tests.cfg_tmpl
zopeskel/unis/templates/unis_plone4_buildout/profiles/etc/backup.cfg_tmpl
zopeskel/unis/templates/unis_plone4_buildout/profiles/etc/balancer.cfg_tmpl
zopeskel/unis/templates/unis_plone4_buildout/profiles/etc/base.cfg_tmpl
zopeskel/unis/templates/unis_plone4_buildout/profiles/etc/cache.cfg_tmpl
zopeskel/unis/templates/unis_plone4_buildout/profiles/etc/defines.cfg_tmpl
zopeskel/unis/templates/unis_plone4_buildout/profiles/etc/http.cfg_tmpl
zopeskel/unis/templates/unis_plone4_buildout/profiles/etc/instance-settings.cfg_tmpl
zopeskel/unis/templates/unis_plone4_buildout/profiles/etc/project.cfg_tmpl
zopeskel/unis/templates/unis_plone4_buildout/profiles/etc/python-ldap.cfg_tmpl
zopeskel/unis/templates/unis_plone4_buildout/profiles/etc/relstorage.cfg_tmpl
zopeskel/unis/templates/unis_plone4_buildout/profiles/etc/sources.cfg_tmpl
zopeskel/unis/templates/unis_plone4_buildout/profiles/etc/supervisor.cfg_tmpl
