Metadata-Version: 1.1
Name: zopeskel.unis
Version: 1.14
Summary: Different kind of buildout templates used by Quadra-Informatique
Home-page: http://github.com/collective/zopeskel.unis
Author: Quadra-Informatique
Author-email: plone@quadra-informatique.fr
License: CeCill-B
Platform: UNKNOWN
Classifier: Programming Language :: Python
Classifier: Development Status :: 5 - Production/Stable
Classifier: Framework :: Plone
Classifier: Framework :: Zope2
Classifier: Intended Audience :: System Administrators
Classifier: Intended Audience :: Education
Classifier: License :: OSI Approved
Classifier: Natural Language :: English
Classifier: Natural Language :: French
Classifier: Operating System :: OS Independent
Classifier: Programming Language :: Python :: 2.6
Classifier: Topic :: Software Development :: Code Generators
Classifier: Topic :: System :: Archiving :: Backup
Classifier: Topic :: System :: Clustering
Classifier: Topic :: System :: Installation/Setup
Classifier: Topic :: Utilities
